ciphers/__init__.py
ciphers/cipher.py
ciphers/cipher_utils.py
ciphers/crypto_backend.py
ciphers/crypto_fernet.py
ciphers/crypto_openssl.py
ciphers/gpg.py
ciphers/libsodium.py
core/__init__.py
core/__main__.py
core/cipherfactory.py
core/collection.py
core/config.py
core/model.py
core/parser.py
core/record.py
core/util.py
core/view.py
core/models/bank_card.json
core/models/business_card.json
core/models/identity.json
core/models/login.json
core/models/raw_text.json
sec_vault-0.1.0.dist-info/LICENSE
sec_vault-0.1.0.dist-info/METADATA
sec_vault-0.1.0.dist-info/WHEEL
sec_vault-0.1.0.dist-info/entry_points.txt
sec_vault-0.1.0.dist-info/top_level.txt
sec_vault-0.1.0.dist-info/RECORD
