Metadata-Version: 2.1
Name: sec-vault
Version: 0.1.0
Summary: Password management CLI
Home-page: https://github.com/siddharths2710/sec-vault
Author: Siddharth Srinivasan
Author-email: siddharths2710@yahoo.com
Maintainer: Siddharth Srinivasan
Maintainer-email: siddharths2710@yahoo.com
License: LGPL-2.1 License
Project-URL: issue_tracker, https://github.com/siddharths2710/sec-vault/issues
Project-URL: download_url, https://github.com/siddharths2710/sec-vault
Keywords: sec-vault,password manager,cryptography,security
Platform: Linux
Platform: MacOS X
Platform: Windows
Classifier: Development Status :: 3 - Alpha
Classifier: Environment :: Console
Classifier: Intended Audience :: Developers
Classifier: License :: OSI Approved :: GNU Lesser General Public License v3 or later (LGPLv3+)
Classifier: Programming Language :: Python :: 3
Classifier: Programming Language :: Python :: 3 :: Only
Classifier: Programming Language :: Python :: 3.6
Classifier: Topic :: Security :: Cryptography
Classifier: Topic :: Utilities
Requires-Python: >=3.6
Requires-Dist: pyyaml
Requires-Dist: argparse
Requires-Dist: python-gnupg (~=0.4.7)
Requires-Dist: cryptography (~=3.4.7)
